notebookjs/__init__.py
notebookjs/_comm.py
notebookjs/_display.py
notebookjs/resources/CommAPI.js
notebookjs/resources/template.html
notebookjs-0.1.4.dist-info/LICENSE
notebookjs-0.1.4.dist-info/METADATA
notebookjs-0.1.4.dist-info/WHEEL
notebookjs-0.1.4.dist-info/top_level.txt
notebookjs-0.1.4.dist-info/RECORD
