Metadata-Version: 2.1
Name: notebookjs
Version: 0.1.4
Summary: notebookJS library - Seamless JavaScript integration in Python Notebooks
Home-page: https://github.com/jorgehpo/notebookJS
Author: Jorge Piazentin Ono, Juliana Freire, Claudio Silva
Author-email: jorgehpo@nyu.edu
License: MIT
Platform: UNKNOWN
Classifier: Programming Language :: Python :: 3
Classifier: License :: OSI Approved :: MIT License
Classifier: Operating System :: OS Independent
Requires-Python: >=3.6
Requires-Dist: notebook
